

    [
        {"id": 1, "name": "Categoria1", "description": "Descrição Categoria1"},
        {"id": 2, "name": "Categoria2", "description": "Descrição Categoria2"},
        {"id": 3, "name": "Categoria3", "description": "Descrição Categoria3"},
        {"id": 4, "name": "Categoria4", "description": "Descrição Categoria4"},
        {"id": 5, "name": "Categoria5", "description": "Descrição Categoria5"},
        {"id": 6, "name": "Categoria6", "description": "Descrição Categoria6"},
        {"id": 7, "name": "Categoria7", "description": "Descrição Categoria7"},
        {"id": 8, "name": "Categoria8", "description": "Descrição Categoria8"},
        {"id": 9, "name": "Categoria9", "description": "Descrição Categoria9"},
        {"id": 10, "name": "Categoria10", "description": "Descrição Categoria10"},
        {"id": 11, "name": "Categoria11", "description": "Descrição Categoria11"},
        {"id": 12, "name": "Categoria12", "description": "Descrição Categoria12"},
        {"id": 13, "name": "Categoria13", "description": "Descrição Categoria13"},
        {"id": 14, "name": "Categoria14", "description": "Descrição Categoria14"},
        {"id": 15, "name": "Categoria15", "description": "Descrição Categoria15"},
        {"id": 16, "name": "Categoria16", "description": "Descrição Categoria16"},
        {"id": 17, "name": "Categoria17", "description": "Descrição Categoria17"},
        {"id": 18, "name": "Categoria18", "description": "Descrição Categoria18"},
        {"id": 19, "name": "Categoria19", "description": "Descrição Categoria19"},
        {"id": 20, "name": "Categoria20", "description": "Descrição Categoria20"},
        {"id": 21, "name": "Categoria21", "description": "Descrição Categoria21"},
        {"id": 22, "name": "Categoria22", "description": "Descrição Categoria22"},
        {"id": 23, "name": "Categoria23", "description": "Descrição Categoria23"},
        {"id": 24, "name": "Categoria24", "description": "Descrição Categoria24"},
        {"id": 25, "name": "Categoria25", "description": "Descrição Categoria25"},
        {"id": 26, "name": "Categoria26", "description": "Descrição Categoria26"},
        {"id": 27, "name": "Categoria27", "description": "Descrição Categoria27"},
        {"id": 28, "name": "Categoria28", "description": "Descrição Categoria28"},
        {"id": 29, "name": "Categoria29", "description": "Descrição Categoria29"},
        {"id": 30, "name": "Categoria30", "description": "Descrição Categoria30"}
                        
    ]

